locoformer/__init__.py
locoformer/locoformer.py
locoformer-0.0.115.dist-info/METADATA
locoformer-0.0.115.dist-info/WHEEL
locoformer-0.0.115.dist-info/licenses/LICENSE
locoformer-0.0.115.dist-info/RECORD
