Metadata-Version: 2.4
Name: locoformer
Version: 0.0.115
Summary: LocoFormer
Project-URL: Homepage, https://pypi.org/project/locoformer/
Project-URL: Repository, https://github.com/lucidrains/locoformer
Author-email: Phil Wang <lucidrains@gmail.com>
License: MIT License
License-File: LICENSE
Keywords: artificial intelligence,attention mechanism,cross-embodiment,deep learning,robotics,transformer
Classifier: Development Status :: 4 - Beta
Classifier: Intended Audience :: Developers
Classifier: License :: OSI Approved :: MIT License
Classifier: Programming Language :: Python :: 3.9
Classifier: Topic :: Scientific/Engineering :: Artificial Intelligence
Requires-Python: >=3.9
Requires-Dist: assoc-scan
Requires-Dist: beartype
Requires-Dist: discrete-continuous-embed-readout>=0.1.11
Requires-Dist: einops>=0.8.0
Requires-Dist: einx>=0.3.0
Requires-Dist: glom
Requires-Dist: hl-gauss-pytorch>=0.2.0
Requires-Dist: memmap-replay-buffer>=0.0.4
Requires-Dist: rotary-embedding-torch
Requires-Dist: torch>=2.8
Requires-Dist: x-evolution>=0.1.23
Requires-Dist: x-mlps-pytorch
Provides-Extra: examples
Requires-Dist: accelerate; extra == 'examples'
Requires-Dist: tqdm; extra == 'examples'
Provides-Extra: test
Requires-Dist: pytest; extra == 'test'
